setup.py
expressmoney/__init__.py
expressmoney/apps/__init__.py
expressmoney/apps/db_config.py
expressmoney/apps/loans/__init__.py
expressmoney/apps/loans/accounting/__init__.py
expressmoney/apps/loans/accounting/admin.py
expressmoney/apps/loans/accounting/apps.py
expressmoney/apps/loans/accounting/models.py
expressmoney/apps/loans/accounting/migrations/__init__.py
expressmoney/apps/loans/black_list/__init__.py
expressmoney/apps/loans/black_list/admin.py
expressmoney/apps/loans/black_list/apps.py
expressmoney/apps/loans/black_list/models.py
expressmoney/apps/loans/black_list/migrations/__init__.py
expressmoney/apps/loans/loans/__init__.py
expressmoney/apps/loans/loans/admin.py
expressmoney/apps/loans/loans/apps.py
expressmoney/apps/loans/loans/models.py
expressmoney/apps/loans/loans/utils.py
expressmoney/apps/loans/loans/migrations/__init__.py
expressmoney/apps/loans/orders/__init__.py
expressmoney/apps/loans/orders/admin.py
expressmoney/apps/loans/orders/apps.py
expressmoney/apps/loans/orders/models.py
expressmoney/apps/loans/orders/migrations/__init__.py
expressmoney/apps/loans/products/__init__.py
expressmoney/apps/loans/products/admin.py
expressmoney/apps/loans/products/apps.py
expressmoney/apps/loans/products/models.py
expressmoney/apps/loans/products/migrations/__init__.py
expressmoney/apps/loans/promocodes/__init__.py
expressmoney/apps/loans/promocodes/admin.py
expressmoney/apps/loans/promocodes/apps.py
expressmoney/apps/loans/promocodes/models.py
expressmoney/apps/loans/promocodes/migrations/__init__.py
expressmoney/apps/profiles/__init__.py
expressmoney/apps/profiles/profiles/__init__.py
expressmoney/apps/profiles/profiles/admin.py
expressmoney/apps/profiles/profiles/apps.py
expressmoney/apps/profiles/profiles/models.py
expressmoney/apps/profiles/profiles/migrations/__init__.py
expressmoney/apps/scoring/__init__.py
expressmoney/apps/scoring/cache/__init__.py
expressmoney/apps/scoring/cache/admin.py
expressmoney/apps/scoring/cache/apps.py
expressmoney_points.egg-info/PKG-INFO
expressmoney_points.egg-info/SOURCES.txt
expressmoney_points.egg-info/dependency_links.txt
expressmoney_points.egg-info/namespace_packages.txt
expressmoney_points.egg-info/top_level.txt